shabti_keycloak/__init__.py
shabti_keycloak-0.1a2.dist-info/METADATA
shabti_keycloak-0.1a2.dist-info/WHEEL
shabti_keycloak-0.1a2.dist-info/RECORD
