Metadata-Version: 2.4
Name: shabti-keycloak
Version: 0.1a2
Requires-Python: >=3.12
Requires-Dist: python-keycloak
